mkdocs_todo_jira/__init__.py
mkdocs_todo_jira/plugin.py
mkdocs_todo_jira-0.1.1.dist-info/METADATA
mkdocs_todo_jira-0.1.1.dist-info/WHEEL
mkdocs_todo_jira-0.1.1.dist-info/entry_points.txt
mkdocs_todo_jira-0.1.1.dist-info/licenses/LICENSE
mkdocs_todo_jira-0.1.1.dist-info/RECORD
