Metadata-Version: 2.1
Name: mkdocs-todo-jira
Version: 0.1.1
Summary: A MkDocs plugin to generate documentation from TODO and BUG comments
Author-email: Bruno <your.email@example.com>
License-Expression: MIT
License-File: LICENSE
Keywords: documentation,jira,mkdocs,todos
Classifier: Development Status :: 4 - Beta
Classifier: Intended Audience :: Developers
Classifier: Intended Audience :: Information Technology
Classifier: License :: OSI Approved :: MIT License
Classifier: Programming Language :: Python
Classifier: Programming Language :: Python :: 3
Classifier: Programming Language :: Python :: 3.4
Classifier: Programming Language :: Python :: 3.5
Classifier: Programming Language :: Python :: 3.6
Classifier: Programming Language :: Python :: 3.7
Requires-Dist: markdown-callouts>=0.1.0
Requires-Dist: mkdocs>=1.4
